{"frames":{"Cop Spaceship0.png":{"frame":{"x":0,"y":0,"w":2000,"h":900},"rotated":false,"trimmed":false,"spriteSourceSize":{"x":0,"y":0,"w":2000,"h":900},"sourceSize":{"w":2000,"h":900}},"Cop Spaceship1.png":{"frame":{"x":2000,"y":0,"w":2000,"h":900},"rotated":false,"trimmed":false,"spriteSourceSize":{"x":0,"y":0,"w":2000,"h":900},"sourceSize":{"w":2000,"h":900}},"Cop Spaceship2.png":{"frame":{"x":4000,"y":0,"w":2000,"h":900},"rotated":false,"trimmed":false,"spriteSourceSize":{"x":0,"y":0,"w":2000,"h":900},"sourceSize":{"w":2000,"h":900}},"Cop Spaceship3.png":{"frame":{"x":6000,"y":0,"w":2000,"h":900},"rotated":false,"trimmed":false,"spriteSourceSize":{"x":0,"y":0,"w":2000,"h":900},"sourceSize":{"w":2000,"h":900}},"Cop Spaceship4.png":{"frame":{"x":8000,"y":0,"w":2000,"h":900},"rotated":false,"trimmed":false,"spriteSourceSize":{"x":0,"y":0,"w":2000,"h":900},"sourceSize":{"w":2000,"h":900}},"Cop Spaceship5.png":{"frame":{"x":10000,"y":0,"w":2000,"h":900},"rotated":false,"trimmed":false,"spriteSourceSize":{"x":0,"y":0,"w":2000,"h":900},"sourceSize":{"w":2000,"h":900}},"Cop Spaceship6.png":{"frame":{"x":0,"y":900,"w":2000,"h":900},"rotated":false,"trimmed":false,"spriteSourceSize":{"x":0,"y":0,"w":2000,"h":900},"sourceSize":{"w":2000,"h":900}},"Cop Spaceship7.png":{"frame":{"x":2000,"y":900,"w":2000,"h":900},"rotated":false,"trimmed":false,"spriteSourceSize":{"x":0,"y":0,"w":2000,"h":900},"sourceSize":{"w":2000,"h":900}},"Cop Spaceship8.png":{"frame":{"x":4000,"y":900,"w":2000,"h":900},"rotated":false,"trimmed":false,"spriteSourceSize":{"x":0,"y":0,"w":2000,"h":900},"sourceSize":{"w":2000,"h":900}},"Cop Spaceship9.png":{"frame":{"x":6000,"y":900,"w":2000,"h":900},"rotated":false,"trimmed":false,"spriteSourceSize":{"x":0,"y":0,"w":2000,"h":900},"sourceSize":{"w":2000,"h":900}},"Cop Spaceship10.png":{"frame":{"x":8000,"y":900,"w":2000,"h":900},"rotated":false,"trimmed":false,"spriteSourceSize":{"x":0,"y":0,"w":2000,"h":900},"sourceSize":{"w":2000,"h":900}},"Cop Spaceship11.png":{"frame":{"x":10000,"y":900,"w":2000,"h":900},"rotated":false,"trimmed":false,"spriteSourceSize":{"x":0,"y":0,"w":2000,"h":900},"sourceSize":{"w":2000,"h":900}},"Cop Spaceship12.png":{"frame":{"x":0,"y":1800,"w":2000,"h":900},"rotated":false,"trimmed":false,"spriteSourceSize":{"x":0,"y":0,"w":2000,"h":900},"sourceSize":{"w":2000,"h":900}},"Cop Spaceship13.png":{"frame":{"x":2000,"y":1800,"w":2000,"h":900},"rotated":false,"trimmed":false,"spriteSourceSize":{"x":0,"y":0,"w":2000,"h":900},"sourceSize":{"w":2000,"h":900}},"Cop Spaceship14.png":{"frame":{"x":4000,"y":1800,"w":2000,"h":900},"rotated":false,"trimmed":false,"spriteSourceSize":{"x":0,"y":0,"w":2000,"h":900},"sourceSize":{"w":2000,"h":900}},"Cop Spaceship15.png":{"frame":{"x":6000,"y":1800,"w":2000,"h":900},"rotated":false,"trimmed":false,"spriteSourceSize":{"x":0,"y":0,"w":2000,"h":900},"sourceSize":{"w":2000,"h":900}},"Cop Spaceship16.png":{"frame":{"x":8000,"y":1800,"w":2000,"h":900},"rotated":false,"trimmed":false,"spriteSourceSize":{"x":0,"y":0,"w":2000,"h":900},"sourceSize":{"w":2000,"h":900}},"Cop Spaceship17.png":{"frame":{"x":10000,"y":1800,"w":2000,"h":900},"rotated":false,"trimmed":false,"spriteSourceSize":{"x":0,"y":0,"w":2000,"h":900},"sourceSize":{"w":2000,"h":900}},"Cop Spaceship18.png":{"frame":{"x":0,"y":2700,"w":2000,"h":900},"rotated":false,"trimmed":false,"spriteSourceSize":{"x":0,"y":0,"w":2000,"h":900},"sourceSize":{"w":2000,"h":900}},"Cop Spaceship19.png":{"frame":{"x":2000,"y":2700,"w":2000,"h":900},"rotated":false,"trimmed":false,"spriteSourceSize":{"x":0,"y":0,"w":2000,"h":900},"sourceSize":{"w":2000,"h":900}},"Cop Spaceship20.png":{"frame":{"x":4000,"y":2700,"w":2000,"h":900},"rotated":false,"trimmed":false,"spriteSourceSize":{"x":0,"y":0,"w":2000,"h":900},"sourceSize":{"w":2000,"h":900}},"Cop Spaceship21.png":{"frame":{"x":6000,"y":2700,"w":2000,"h":900},"rotated":false,"trimmed":false,"spriteSourceSize":{"x":0,"y":0,"w":2000,"h":900},"sourceSize":{"w":2000,"h":900}},"Cop Spaceship22.png":{"frame":{"x":8000,"y":2700,"w":2000,"h":900},"rotated":false,"trimmed":false,"spriteSourceSize":{"x":0,"y":0,"w":2000,"h":900},"sourceSize":{"w":2000,"h":900}},"Cop Spaceship23.png":{"frame":{"x":10000,"y":2700,"w":2000,"h":900},"rotated":false,"trimmed":false,"spriteSourceSize":{"x":0,"y":0,"w":2000,"h":900},"sourceSize":{"w":2000,"h":900}},"Cop Spaceship24.png":{"frame":{"x":0,"y":3600,"w":2000,"h":900},"rotated":false,"trimmed":false,"spriteSourceSize":{"x":0,"y":0,"w":2000,"h":900},"sourceSize":{"w":2000,"h":900}},"Cop Spaceship25.png":{"frame":{"x":2000,"y":3600,"w":2000,"h":900},"rotated":false,"trimmed":false,"spriteSourceSize":{"x":0,"y":0,"w":2000,"h":900},"sourceSize":{"w":2000,"h":900}},"Cop Spaceship26.png":{"frame":{"x":4000,"y":3600,"w":2000,"h":900},"rotated":false,"trimmed":false,"spriteSourceSize":{"x":0,"y":0,"w":2000,"h":900},"sourceSize":{"w":2000,"h":900}},"Cop Spaceship27.png":{"frame":{"x":6000,"y":3600,"w":2000,"h":900},"rotated":false,"trimmed":false,"spriteSourceSize":{"x":0,"y":0,"w":2000,"h":900},"sourceSize":{"w":2000,"h":900}},"Cop Spaceship28.png":{"frame":{"x":8000,"y":3600,"w":2000,"h":900},"rotated":false,"trimmed":false,"spriteSourceSize":{"x":0,"y":0,"w":2000,"h":900},"sourceSize":{"w":2000,"h":900}},"Cop Spaceship29.png":{"frame":{"x":10000,"y":3600,"w":2000,"h":900},"rotated":false,"trimmed":false,"spriteSourceSize":{"x":0,"y":0,"w":2000,"h":900},"sourceSize":{"w":2000,"h":900}},"Cop Spaceship30.png":{"frame":{"x":0,"y":4500,"w":2000,"h":900},"rotated":false,"trimmed":false,"spriteSourceSize":{"x":0,"y":0,"w":2000,"h":900},"sourceSize":{"w":2000,"h":900}},"Cop Spaceship31.png":{"frame":{"x":2000,"y":4500,"w":2000,"h":900},"rotated":false,"trimmed":false,"spriteSourceSize":{"x":0,"y":0,"w":2000,"h":900},"sourceSize":{"w":2000,"h":900}},"Cop Spaceship32.png":{"frame":{"x":4000,"y":4500,"w":2000,"h":900},"rotated":false,"trimmed":false,"spriteSourceSize":{"x":0,"y":0,"w":2000,"h":900},"sourceSize":{"w":2000,"h":900}},"Cop Spaceship33.png":{"frame":{"x":6000,"y":4500,"w":2000,"h":900},"rotated":false,"trimmed":false,"spriteSourceSize":{"x":0,"y":0,"w":2000,"h":900},"sourceSize":{"w":2000,"h":900}},"Cop Spaceship34.png":{"frame":{"x":8000,"y":4500,"w":2000,"h":900},"rotated":false,"trimmed":false,"spriteSourceSize":{"x":0,"y":0,"w":2000,"h":900},"sourceSize":{"w":2000,"h":900}},"Cop Spaceship35.png":{"frame":{"x":10000,"y":4500,"w":2000,"h":900},"rotated":false,"trimmed":false,"spriteSourceSize":{"x":0,"y":0,"w":2000,"h":900},"sourceSize":{"w":2000,"h":900}},"Cop Spaceship36.png":{"frame":{"x":0,"y":5400,"w":2000,"h":900},"rotated":false,"trimmed":false,"spriteSourceSize":{"x":0,"y":0,"w":2000,"h":900},"sourceSize":{"w":2000,"h":900}},"Cop Spaceship37.png":{"frame":{"x":2000,"y":5400,"w":2000,"h":900},"rotated":false,"trimmed":false,"spriteSourceSize":{"x":0,"y":0,"w":2000,"h":900},"sourceSize":{"w":2000,"h":900}},"Cop Spaceship38.png":{"frame":{"x":4000,"y":5400,"w":2000,"h":900},"rotated":false,"trimmed":false,"spriteSourceSize":{"x":0,"y":0,"w":2000,"h":900},"sourceSize":{"w":2000,"h":900}},"Cop Spaceship39.png":{"frame":{"x":6000,"y":5400,"w":2000,"h":900},"rotated":false,"trimmed":false,"spriteSourceSize":{"x":0,"y":0,"w":2000,"h":900},"sourceSize":{"w":2000,"h":900}},"Cop Spaceship40.png":{"frame":{"x":8000,"y":5400,"w":2000,"h":900},"rotated":false,"trimmed":false,"spriteSourceSize":{"x":0,"y":0,"w":2000,"h":900},"sourceSize":{"w":2000,"h":900}},"Cop Spaceship41.png":{"frame":{"x":10000,"y":5400,"w":2000,"h":900},"rotated":false,"trimmed":false,"spriteSourceSize":{"x":0,"y":0,"w":2000,"h":900},"sourceSize":{"w":2000,"h":900}},"Cop Spaceship42.png":{"frame":{"x":0,"y":6300,"w":2000,"h":900},"rotated":false,"trimmed":false,"spriteSourceSize":{"x":0,"y":0,"w":2000,"h":900},"sourceSize":{"w":2000,"h":900}},"Cop Spaceship43.png":{"frame":{"x":2000,"y":6300,"w":2000,"h":900},"rotated":false,"trimmed":false,"spriteSourceSize":{"x":0,"y":0,"w":2000,"h":900},"sourceSize":{"w":2000,"h":900}},"Cop Spaceship44.png":{"frame":{"x":4000,"y":6300,"w":2000,"h":900},"rotated":false,"trimmed":false,"spriteSourceSize":{"x":0,"y":0,"w":2000,"h":900},"sourceSize":{"w":2000,"h":900}},"Cop Spaceship45.png":{"frame":{"x":6000,"y":6300,"w":2000,"h":900},"rotated":false,"trimmed":false,"spriteSourceSize":{"x":0,"y":0,"w":2000,"h":900},"sourceSize":{"w":2000,"h":900}},"Cop Spaceship46.png":{"frame":{"x":8000,"y":6300,"w":2000,"h":900},"rotated":false,"trimmed":false,"spriteSourceSize":{"x":0,"y":0,"w":2000,"h":900},"sourceSize":{"w":2000,"h":900}},"Cop Spaceship47.png":{"frame":{"x":10000,"y":6300,"w":2000,"h":900},"rotated":false,"trimmed":false,"spriteSourceSize":{"x":0,"y":0,"w":2000,"h":900},"sourceSize":{"w":2000,"h":900}},"Cop Spaceship48.png":{"frame":{"x":0,"y":7200,"w":2000,"h":900},"rotated":false,"trimmed":false,"spriteSourceSize":{"x":0,"y":0,"w":2000,"h":900},"sourceSize":{"w":2000,"h":900}},"Cop Spaceship49.png":{"frame":{"x":2000,"y":7200,"w":2000,"h":900},"rotated":false,"trimmed":false,"spriteSourceSize":{"x":0,"y":0,"w":2000,"h":900},"sourceSize":{"w":2000,"h":900}},"Cop Spaceship50.png":{"frame":{"x":4000,"y":7200,"w":2000,"h":900},"rotated":false,"trimmed":false,"spriteSourceSize":{"x":0,"y":0,"w":2000,"h":900},"sourceSize":{"w":2000,"h":900}},"Cop Spaceship51.png":{"frame":{"x":6000,"y":7200,"w":2000,"h":900},"rotated":false,"trimmed":false,"spriteSourceSize":{"x":0,"y":0,"w":2000,"h":900},"sourceSize":{"w":2000,"h":900}},"Cop Spaceship52.png":{"frame":{"x":8000,"y":7200,"w":2000,"h":900},"rotated":false,"trimmed":false,"spriteSourceSize":{"x":0,"y":0,"w":2000,"h":900},"sourceSize":{"w":2000,"h":900}},"Cop Spaceship53.png":{"frame":{"x":10000,"y":7200,"w":2000,"h":900},"rotated":false,"trimmed":false,"spriteSourceSize":{"x":0,"y":0,"w":2000,"h":900},"sourceSize":{"w":2000,"h":900}},"Cop Spaceship54.png":{"frame":{"x":0,"y":8100,"w":2000,"h":900},"rotated":false,"trimmed":false,"spriteSourceSize":{"x":0,"y":0,"w":2000,"h":900},"sourceSize":{"w":2000,"h":900}},"Cop Spaceship55.png":{"frame":{"x":2000,"y":8100,"w":2000,"h":900},"rotated":false,"trimmed":false,"spriteSourceSize":{"x":0,"y":0,"w":2000,"h":900},"sourceSize":{"w":2000,"h":900}},"Cop Spaceship56.png":{"frame":{"x":4000,"y":8100,"w":2000,"h":900},"rotated":false,"trimmed":false,"spriteSourceSize":{"x":0,"y":0,"w":2000,"h":900},"sourceSize":{"w":2000,"h":900}},"Cop Spaceship57.png":{"frame":{"x":6000,"y":8100,"w":2000,"h":900},"rotated":false,"trimmed":false,"spriteSourceSize":{"x":0,"y":0,"w":2000,"h":900},"sourceSize":{"w":2000,"h":900}},"Cop Spaceship58.png":{"frame":{"x":8000,"y":8100,"w":2000,"h":900},"rotated":false,"trimmed":false,"spriteSourceSize":{"x":0,"y":0,"w":2000,"h":900},"sourceSize":{"w":2000,"h":900}},"Cop Spaceship59.png":{"frame":{"x":10000,"y":8100,"w":2000,"h":900},"rotated":false,"trimmed":false,"spriteSourceSize":{"x":0,"y":0,"w":2000,"h":900},"sourceSize":{"w":2000,"h":900}},"Cop Spaceship60.png":{"frame":{"x":0,"y":9000,"w":2000,"h":900},"rotated":false,"trimmed":false,"spriteSourceSize":{"x":0,"y":0,"w":2000,"h":900},"sourceSize":{"w":2000,"h":900}},"Cop Spaceship61.png":{"frame":{"x":2000,"y":9000,"w":2000,"h":900},"rotated":false,"trimmed":false,"spriteSourceSize":{"x":0,"y":0,"w":2000,"h":900},"sourceSize":{"w":2000,"h":900}},"Cop Spaceship62.png":{"frame":{"x":4000,"y":9000,"w":2000,"h":900},"rotated":false,"trimmed":false,"spriteSourceSize":{"x":0,"y":0,"w":2000,"h":900},"sourceSize":{"w":2000,"h":900}},"Cop Spaceship63.png":{"frame":{"x":6000,"y":9000,"w":2000,"h":900},"rotated":false,"trimmed":false,"spriteSourceSize":{"x":0,"y":0,"w":2000,"h":900},"sourceSize":{"w":2000,"h":900}},"Cop Spaceship64.png":{"frame":{"x":8000,"y":9000,"w":2000,"h":900},"rotated":false,"trimmed":false,"spriteSourceSize":{"x":0,"y":0,"w":2000,"h":900},"sourceSize":{"w":2000,"h":900}},"Cop Spaceship65.png":{"frame":{"x":10000,"y":9000,"w":2000,"h":900},"rotated":false,"trimmed":false,"spriteSourceSize":{"x":0,"y":0,"w":2000,"h":900},"sourceSize":{"w":2000,"h":900}},"Cop Spaceship66.png":{"frame":{"x":0,"y":9900,"w":2000,"h":900},"rotated":false,"trimmed":false,"spriteSourceSize":{"x":0,"y":0,"w":2000,"h":900},"sourceSize":{"w":2000,"h":900}},"Cop Spaceship67.png":{"frame":{"x":2000,"y":9900,"w":2000,"h":900},"rotated":false,"trimmed":false,"spriteSourceSize":{"x":0,"y":0,"w":2000,"h":900},"sourceSize":{"w":2000,"h":900}},"Cop Spaceship68.png":{"frame":{"x":4000,"y":9900,"w":2000,"h":900},"rotated":false,"trimmed":false,"spriteSourceSize":{"x":0,"y":0,"w":2000,"h":900},"sourceSize":{"w":2000,"h":900}},"Cop Spaceship69.png":{"frame":{"x":6000,"y":9900,"w":2000,"h":900},"rotated":false,"trimmed":false,"spriteSourceSize":{"x":0,"y":0,"w":2000,"h":900},"sourceSize":{"w":2000,"h":900}},"Cop Spaceship70.png":{"frame":{"x":8000,"y":9900,"w":2000,"h":900},"rotated":false,"trimmed":false,"spriteSourceSize":{"x":0,"y":0,"w":2000,"h":900},"sourceSize":{"w":2000,"h":900}},"Cop Spaceship71.png":{"frame":{"x":10000,"y":9900,"w":2000,"h":900},"rotated":false,"trimmed":false,"spriteSourceSize":{"x":0,"y":0,"w":2000,"h":900},"sourceSize":{"w":2000,"h":900}},"Cop Spaceship72.png":{"frame":{"x":0,"y":10800,"w":2000,"h":900},"rotated":false,"trimmed":false,"spriteSourceSize":{"x":0,"y":0,"w":2000,"h":900},"sourceSize":{"w":2000,"h":900}},"Cop Spaceship73.png":{"frame":{"x":2000,"y":10800,"w":2000,"h":900},"rotated":false,"trimmed":false,"spriteSourceSize":{"x":0,"y":0,"w":2000,"h":900},"sourceSize":{"w":2000,"h":900}},"Cop Spaceship74.png":{"frame":{"x":4000,"y":10800,"w":2000,"h":900},"rotated":false,"trimmed":false,"spriteSourceSize":{"x":0,"y":0,"w":2000,"h":900},"sourceSize":{"w":2000,"h":900}},"Cop Spaceship75.png":{"frame":{"x":6000,"y":10800,"w":2000,"h":900},"rotated":false,"trimmed":false,"spriteSourceSize":{"x":0,"y":0,"w":2000,"h":900},"sourceSize":{"w":2000,"h":900}},"Cop Spaceship76.png":{"frame":{"x":8000,"y":10800,"w":2000,"h":900},"rotated":false,"trimmed":false,"spriteSourceSize":{"x":0,"y":0,"w":2000,"h":900},"sourceSize":{"w":2000,"h":900}},"Cop Spaceship77.png":{"frame":{"x":10000,"y":10800,"w":2000,"h":900},"rotated":false,"trimmed":false,"spriteSourceSize":{"x":0,"y":0,"w":2000,"h":900},"sourceSize":{"w":2000,"h":900}},"Cop Spaceship78.png":{"frame":{"x":0,"y":11700,"w":2000,"h":900},"rotated":false,"trimmed":false,"spriteSourceSize":{"x":0,"y":0,"w":2000,"h":900},"sourceSize":{"w":2000,"h":900}},"Cop Spaceship79.png":{"frame":{"x":2000,"y":11700,"w":2000,"h":900},"rotated":false,"trimmed":false,"spriteSourceSize":{"x":0,"y":0,"w":2000,"h":900},"sourceSize":{"w":2000,"h":900}},"Cop Spaceship80.png":{"frame":{"x":4000,"y":11700,"w":2000,"h":900},"rotated":false,"trimmed":false,"spriteSourceSize":{"x":0,"y":0,"w":2000,"h":900},"sourceSize":{"w":2000,"h":900}},"Cop Spaceship81.png":{"frame":{"x":6000,"y":11700,"w":2000,"h":900},"rotated":false,"trimmed":false,"spriteSourceSize":{"x":0,"y":0,"w":2000,"h":900},"sourceSize":{"w":2000,"h":900}},"Cop Spaceship82.png":{"frame":{"x":8000,"y":11700,"w":2000,"h":900},"rotated":false,"trimmed":false,"spriteSourceSize":{"x":0,"y":0,"w":2000,"h":900},"sourceSize":{"w":2000,"h":900}},"Cop Spaceship83.png":{"frame":{"x":10000,"y":11700,"w":2000,"h":900},"rotated":false,"trimmed":false,"spriteSourceSize":{"x":0,"y":0,"w":2000,"h":900},"sourceSize":{"w":2000,"h":900}},"Cop Spaceship84.png":{"frame":{"x":0,"y":12600,"w":2000,"h":900},"rotated":false,"trimmed":false,"spriteSourceSize":{"x":0,"y":0,"w":2000,"h":900},"sourceSize":{"w":2000,"h":900}},"Cop Spaceship85.png":{"frame":{"x":2000,"y":12600,"w":2000,"h":900},"rotated":false,"trimmed":false,"spriteSourceSize":{"x":0,"y":0,"w":2000,"h":900},"sourceSize":{"w":2000,"h":900}},"Cop Spaceship86.png":{"frame":{"x":4000,"y":12600,"w":2000,"h":900},"rotated":false,"trimmed":false,"spriteSourceSize":{"x":0,"y":0,"w":2000,"h":900},"sourceSize":{"w":2000,"h":900}},"Cop Spaceship87.png":{"frame":{"x":6000,"y":12600,"w":2000,"h":900},"rotated":false,"trimmed":false,"spriteSourceSize":{"x":0,"y":0,"w":2000,"h":900},"sourceSize":{"w":2000,"h":900}},"Cop Spaceship88.png":{"frame":{"x":8000,"y":12600,"w":2000,"h":900},"rotated":false,"trimmed":false,"spriteSourceSize":{"x":0,"y":0,"w":2000,"h":900},"sourceSize":{"w":2000,"h":900}},"Cop Spaceship89.png":{"frame":{"x":10000,"y":12600,"w":2000,"h":900},"rotated":false,"trimmed":false,"spriteSourceSize":{"x":0,"y":0,"w":2000,"h":900},"sourceSize":{"w":2000,"h":900}},"Cop Spaceship90.png":{"frame":{"x":0,"y":13500,"w":2000,"h":900},"rotated":false,"trimmed":false,"spriteSourceSize":{"x":0,"y":0,"w":2000,"h":900},"sourceSize":{"w":2000,"h":900}},"Cop Spaceship91.png":{"frame":{"x":2000,"y":13500,"w":2000,"h":900},"rotated":false,"trimmed":false,"spriteSourceSize":{"x":0,"y":0,"w":2000,"h":900},"sourceSize":{"w":2000,"h":900}},"Cop Spaceship92.png":{"frame":{"x":4000,"y":13500,"w":2000,"h":900},"rotated":false,"trimmed":false,"spriteSourceSize":{"x":0,"y":0,"w":2000,"h":900},"sourceSize":{"w":2000,"h":900}}},"meta":{"app":"https://github.com/piskelapp/piskel/","version":"1.0","image":"Cop Spaceship.png","format":"RGBA8888","size":{"w":12000,"h":14400}}}